hoymilesdtumi/__init__.py
hoymilesdtumi/hoymilesdtumi.py
hoymilesdtumi-0.0.3.dist-info/LICENSE
hoymilesdtumi-0.0.3.dist-info/METADATA
hoymilesdtumi-0.0.3.dist-info/WHEEL
hoymilesdtumi-0.0.3.dist-info/top_level.txt
hoymilesdtumi-0.0.3.dist-info/RECORD
