Metadata-Version: 2.1
Name: hoymilesdtumi
Version: 0.0.3
Summary: Hoymiles DTU-MI data wrapper for python.
Home-page: https://github.com/sileandro/hoymilesdtumi
Author: Silvio Lima
Author-email: dev.silvio@gmail.com
License: UNKNOWN
Platform: UNKNOWN
Classifier: Programming Language :: Python :: 3
Classifier: License :: OSI Approved :: MIT License
Classifier: Operating System :: OS Independent
Requires-Python: >=3.6
